dism/__init__.py
dism-3.0.0.dist-info/METADATA
dism-3.0.0.dist-info/WHEEL
dism-3.0.0.dist-info/licenses/LICENSE
dism-3.0.0.dist-info/RECORD
