Metadata-Version: 2.4
Name: dism
Version: 3.0.0
Summary: Easily use Microsoft's DISM Command-Line Interface in Python.
Project-URL: Homepage, https://github.com/samuellouf/DISM
Project-URL: Issues, https://github.com/samuellouf/DISM/issues
Author: SamuelLouf
License-File: LICENSE
Classifier: Development Status :: 5 - Production/Stable
Classifier: Environment :: Console
Classifier: Intended Audience :: Developers
Classifier: License :: OSI Approved :: MIT License
Classifier: Natural Language :: English
Classifier: Operating System :: Microsoft :: Windows
Classifier: Operating System :: Microsoft :: Windows :: Windows 10
Classifier: Operating System :: Microsoft :: Windows :: Windows 11
Classifier: Programming Language :: Python :: 3
Classifier: Topic :: Software Development
Classifier: Topic :: System
Classifier: Topic :: System :: Boot
Classifier: Topic :: System :: Installation/Setup
Classifier: Topic :: System :: Operating System
Requires-Python: >=3
